Workbook

Sheet Resumo_Executivo
A1: Indicador | B1: Formula/Valor | C1: Interpretacao
A2: Valor base | B2: =Premissas!B2 | C2: Referencia da clausula 5
A3: Valor com contingencia | B3: =Premissas!B2*(1+Premissas!B3) | C3: Preco base mais reserva tecnica
A4: Total liquido por marcos | B4: =SUM(Cronograma_Desembolso!G2:G6) | C4: Soma da aba Cronograma_Desembolso
A5: Total custo por perfis | B5: =SUM(Custo_Perfis!D2:D8) | C5: Soma da aba Custo_Perfis
A6: Margem antes de impostos | B6: =B4-B5 | C6: Diferenca entre liquido e custos
A7: Creditos SLA estimados | B7: =SUM(SLA_Creditos!D2:D5) | C7: Soma da aba SLA_Creditos

Sheet Premissas
A1: Parametro | B1: Valor | C1: Unidade | D1: Observacao
A2: Preco base | B2: 1284000 | C2: BRL | D2: Valor antes de contingencia e reajuste
A3: Contingencia | B3: 0.08 | C3: % | D3: Reserva tecnica para riscos aprovados
A4: IPCA acumulado | B4: 0.052 | C4: % | D4: Exemplo sintetico para teste
A5: Gatilho reajuste | B5: 0.04 | C5: % | D5: Reajuste apenas acima do gatilho
A6: Limite credito atraso | B6: 0.08 | C6: % | D6: Teto por marco afetado
A7: Credito diario atraso | B7: 0.0015 | C7: % | D7: 0,15% ao dia
A8: SLA contratado | B8: 0.995 | C8: % | D8: Disponibilidade mensal minima

Sheet Cronograma_Desembolso
A1: Marco | B1: Percentual | C1: Valor Base | D1: Reajuste Aplicavel | E1: Valor Corrigido | F1: Credito Atraso | G1: Valor Liquido
A2: M1 | B2: 0.15 | C2: =Premissas!B2*B2 | D2: =MAX(Premissas!B4-Premissas!B5,0)*C2 | E2: =C2+D2 | F2: =MIN(0*Premissas!B7*C2,Premissas!B6*C2) | G2: =E2-F2
A3: M2 | B3: 0.25 | C3: =Premissas!B2*B3 | D3: =MAX(Premissas!B4-Premissas!B5,0)*C3 | E3: =C3+D3 | F3: =MIN(0*Premissas!B7*C3,Premissas!B6*C3) | G3: =E3-F3
A4: M3 | B4: 0.25 | C4: =Premissas!B2*B4 | D4: =MAX(Premissas!B4-Premissas!B5,0)*C4 | E4: =C4+D4 | F4: =MIN(7*Premissas!B7*C4,Premissas!B6*C4) | G4: =E4-F4
A5: M4 | B5: 0.25 | C5: =Premissas!B2*B5 | D5: =MAX(Premissas!B4-Premissas!B5,0)*C5 | E5: =C5+D5 | F5: =MIN(12*Premissas!B7*C5,Premissas!B6*C5) | G5: =E5-F5
A6: M5 | B6: 0.1 | C6: =Premissas!B2*B6 | D6: =MAX(Premissas!B4-Premissas!B5,0)*C6 | E6: =C6+D6 | F6: =MIN(0*Premissas!B7*C6,Premissas!B6*C6) | G6: =E6-F6

Sheet Custo_Perfis
A1: Perfil | B1: Horas | C1: Taxa Hora | D1: Custo | E1: Observacao
A2: Arquiteto | B2: 420 | C2: 390 | D2: =B2*C2 | E2: Base sintetica para confrontar valor contratual
A3: Engenheiro Backend | B3: 1320 | C3: 280 | D3: =B3*C3 | E3: Base sintetica para confrontar valor contratual
A4: Engenheiro Frontend | B4: 640 | C4: 245 | D4: =B4*C4 | E4: Base sintetica para confrontar valor contratual
A5: Engenheiro Dados/ML | B5: 760 | C5: 330 | D5: =B5*C5 | E5: Base sintetica para confrontar valor contratual
A6: QA Automacao | B6: 520 | C6: 210 | D6: =B6*C6 | E6: Base sintetica para confrontar valor contratual
A7: Gestao Projeto | B7: 360 | C7: 260 | D7: =B7*C7 | E7: Base sintetica para confrontar valor contratual
A8: Seguranca | B8: 180 | C8: 420 | D8: =B8*C8 | E8: Base sintetica para confrontar valor contratual

Sheet SLA_Creditos
A1: Mes | B1: Disponibilidade | C1: Base Mensal | D1: Credito SLA | E1: Regra
A2: 2026-10 | B2: 0.997 | C2: 256800 | D2: =IF(B2>=Premissas!B8,0,MIN((Premissas!B8-B2)*10*C2,0.06*C2)) | E2: Se abaixo de 99,50%, credito proporcional com teto de 6%
A3: 2026-11 | B3: 0.991 | C3: 321000 | D3: =IF(B3>=Premissas!B8,0,MIN((Premissas!B8-B3)*10*C3,0.06*C3)) | E3: Se abaixo de 99,50%, credito proporcional com teto de 6%
A4: 2026-12 | B4: 0.986 | C4: 321000 | D4: =IF(B4>=Premissas!B8,0,MIN((Premissas!B8-B4)*10*C4,0.06*C4)) | E4: Se abaixo de 99,50%, credito proporcional com teto de 6%
A5: 2027-01 | B5: 0.996 | C5: 256800 | D5: =IF(B5>=Premissas!B8,0,MIN((Premissas!B8-B5)*10*C5,0.06*C5)) | E5: Se abaixo de 99,50%, credito proporcional com teto de 6%
